djangocms_xliff/__init__.py
djangocms_xliff/admin.py
djangocms_xliff/apps.py
djangocms_xliff/cms_toolbars.py
djangocms_xliff/exceptions.py
djangocms_xliff/exports.py
djangocms_xliff/extractors.py
djangocms_xliff/forms.py
djangocms_xliff/imports.py
djangocms_xliff/parsers.py
djangocms_xliff/renderer.py
djangocms_xliff/settings.py
djangocms_xliff/types.py
djangocms_xliff/urls.py
djangocms_xliff/utils.py
djangocms_xliff/views.py
djangocms_xliff/locale/de/LC_MESSAGES/django.mo
djangocms_xliff/locale/de/LC_MESSAGES/django.po
djangocms_xliff/management/__init__.py
djangocms_xliff/management/commands/__init__.py
djangocms_xliff/management/commands/xliff_export.py
djangocms_xliff/management/commands/xliff_import.py
djangocms_xliff/management/commands/xliff_page_plugins.py
djangocms_xliff/templates/djangocms_xliff/base.html
djangocms_xliff/templates/djangocms_xliff/error.html
djangocms_xliff/templates/djangocms_xliff/admin/xliff/change_list.html
djangocms_xliff/templates/djangocms_xliff/admin/xliff/error.html
djangocms_xliff/templates/djangocms_xliff/admin/xliff/form_fields.html
djangocms_xliff/templates/djangocms_xliff/admin/xliff/overview.html
djangocms_xliff/templates/djangocms_xliff/admin/xliff/preview.html
djangocms_xliff/templates/djangocms_xliff/export/index.html
djangocms_xliff/templates/djangocms_xliff/export/v1.2.xliff
djangocms_xliff/templates/djangocms_xliff/import/preview.html
djangocms_xliff/templates/djangocms_xliff/import/success.html
djangocms_xliff/templates/djangocms_xliff/import/upload.html
djangocms_xliff-2.0.4.dist-info/METADATA
djangocms_xliff-2.0.4.dist-info/WHEEL
djangocms_xliff-2.0.4.dist-info/licenses/LICENSE
djangocms_xliff-2.0.4.dist-info/RECORD
