Metadata-Version: 2.4
Name: djangocms-xliff
Version: 2.0.4
Summary: XLIFF Import and Export for the Django CMS
Project-URL: Homepage, https://energie360.ch
Project-URL: Repository, https://github.com/energie360/djangocms-xliff
Author-email: Energie 360 <onlineservice@energie360.ch>
Maintainer-email: Energie 360 <onlineservice@energie360.ch>
License-Expression: MIT
License-File: LICENSE
Keywords: django,django-cms,export,import,xliff
Classifier: Environment :: Web Environment
Classifier: Framework :: Django
Classifier: Framework :: Django CMS
Classifier: License :: OSI Approved :: MIT License
Classifier: Operating System :: OS Independent
Classifier: Programming Language :: Python
Classifier: Programming Language :: Python :: 3
Classifier: Topic :: Internet :: WWW/HTTP
Classifier: Topic :: Internet :: WWW/HTTP :: Dynamic Content
Classifier: Topic :: Software Development :: Libraries
Requires-Python: >=3.13
Requires-Dist: defusedxml>=0.7
Requires-Dist: django-cms>=5.0
Requires-Dist: django<6.0,>=3.2
Requires-Dist: djangocms-alias>=2.0
